pychart/__init__.py
pychart/linea.py
pychart/mapper.py
pychart/pychart.py
PyChart_busnellistefano-1.1.0.dist-info/LICENSE
PyChart_busnellistefano-1.1.0.dist-info/METADATA
PyChart_busnellistefano-1.1.0.dist-info/WHEEL
PyChart_busnellistefano-1.1.0.dist-info/top_level.txt
PyChart_busnellistefano-1.1.0.dist-info/RECORD
