Metadata-Version: 2.1
Name: PyChart-busnellistefano
Version: 1.1.0
Summary: A simple chart class
Home-page: https://bitbucket.org/StefanoBusnelli/pychart
Author: Busnelli Stefano Antonio
Author-email: busnelli.stefano@gmail.com
License: UNKNOWN
Platform: UNKNOWN
Classifier: Programming Language :: Python :: 3.9
Classifier: License :: OSI Approved :: MIT License
Classifier: Operating System :: OS Independent
License-File: LICENSE
Requires-Dist: Pillow
